💎_ULTIMATE_DOWNLOAD_TRACKER.py
cellrepair_ai/cellrepair_intelligence.py
cellrepair_ai-2.0.0.dist-info/METADATA
cellrepair_ai-2.0.0.dist-info/WHEEL
cellrepair_ai-2.0.0.dist-info/top_level.txt
cellrepair_ai-2.0.0.dist-info/RECORD
