Metadata-Version: 2.4
Name: cellrepair-ai
Version: 2.0.0
Summary: CellRepair.AI - Evolutionäres KI-Framework mit 12 Genie-Level-Features
Home-page: https://cellrepair.ai
Author: Oliver Winkel
Author-email: Oliver Winkel <ai@cellrepair.ai>
License: PROPRIETARY
Project-URL: Homepage, https://cellrepair.ai
Project-URL: Documentation, https://cellrepair.ai/docs
Project-URL: API, https://cellrepair.ai/api/docs
Project-URL: GitHub, https://github.com/cellrepair/cellrepair-ai
Project-URL: Issues, https://github.com/cellrepair/cellrepair-ai/issues
Project-URL: Pricing, https://cellrepair.ai/pricing
Keywords: ai,artificial-intelligence,genie-level,evolutionary-framework,self-healing,predictive-load-indexing,empathy-matrix,meta-proxy-bus,neural-autodiagnosis,situation-synthesis,meta-reflection,agent-resonance,antiproblem-generator,dynamic-subagents,cellrepair,aurora-genesis
Classifier: Development Status :: 5 - Production/Stable
Classifier: Intended Audience :: Developers
Classifier: Intended Audience :: Science/Research
Classifier: Intended Audience :: Healthcare Industry
Classifier: Topic :: Scientific/Engineering :: Artificial Intelligence
Classifier: Topic :: Software Development :: Libraries :: Python Modules
Classifier: License :: Other/Proprietary License
Classifier: Programming Language :: Python :: 3
Classifier: Programming Language :: Python :: 3.9
Classifier: Programming Language :: Python :: 3.10
Classifier: Programming Language :: Python :: 3.11
Classifier: Programming Language :: Python :: 3.12
Classifier: Operating System :: OS Independent
Requires-Python: >=3.9
Requires-Dist: flask>=3.0.0
Requires-Dist: psutil>=5.9.0
Requires-Dist: requests>=2.31.0
Requires-Dist: stripe>=7.0.0
Requires-Dist: python-dotenv>=1.0.0
Provides-Extra: dev
Requires-Dist: pytest>=7.4.0; extra == "dev"
Requires-Dist: pytest-cov>=4.1.0; extra == "dev"
Requires-Dist: black>=23.0.0; extra == "dev"
Requires-Dist: flake8>=6.0.0; extra == "dev"
Requires-Dist: mypy>=1.5.0; extra == "dev"
Provides-Extra: all
Requires-Dist: openai>=1.0.0; extra == "all"
Requires-Dist: anthropic>=0.7.0; extra == "all"
Requires-Dist: google-generativeai>=0.3.0; extra == "all"
Requires-Dist: perplexity>=0.1.0; extra == "all"
Dynamic: author
Dynamic: home-page
Dynamic: requires-python
